guildbot/__init__.py
guildbot/event.py
guildbot/guildbot.py
guildbot/utils.py
better_qq_botpy-0.1.0.dist-info/LICENSE
better_qq_botpy-0.1.0.dist-info/METADATA
better_qq_botpy-0.1.0.dist-info/WHEEL
better_qq_botpy-0.1.0.dist-info/top_level.txt
better_qq_botpy-0.1.0.dist-info/RECORD
